fustor_registry/__init__.py
fustor_registry/cli.py
fustor_registry/client.py
fustor_registry/config.py
fustor_registry/database.py
fustor_registry/main.py
fustor_registry/models.py
fustor_registry/schemas.py
fustor_registry/security.py
fustor_registry/admin/__init__.py
fustor_registry/admin/model.py
fustor_registry/admin/router.py
fustor_registry/api/client/api.py
fustor_registry/apikey/__init__.py
fustor_registry/apikey/router.py
fustor_registry/auth/__init__.py
fustor_registry/auth/model.py
fustor_registry/auth/router.py
fustor_registry/datastore/__init__.py
fustor_registry/datastore/model.py
fustor_registry/datastore/router.py
fustor_registry/profile/__init__.py
fustor_registry/profile/model.py
fustor_registry/profile/router.py
fustor_registry/ui/index.html
fustor_registry/ui/assets/css/style.css
fustor_registry/ui/assets/js/api.js
fustor_registry/ui/assets/js/app.js
fustor_registry/ui/assets/js/ui.js
fustor_registry-0.2.16.dist-info/METADATA
fustor_registry-0.2.16.dist-info/WHEEL
fustor_registry-0.2.16.dist-info/entry_points.txt
fustor_registry-0.2.16.dist-info/top_level.txt
fustor_registry-0.2.16.dist-info/RECORD
