Metadata-Version: 2.4
Name: fustor-registry
Version: 0.2.16
Summary: Registry service for Fustor (Control Plane)
Author-email: Huajin Wang <wanghuajin999@163.com>
Requires-Python: >=3.11
Requires-Dist: click
Requires-Dist: fastapi[all]
Requires-Dist: uvicorn
Requires-Dist: pydantic
Requires-Dist: pydantic-settings
Requires-Dist: greenlet==3.2.2
Requires-Dist: sqlalchemy==2.0.41
Requires-Dist: aiosqlite
Requires-Dist: passlib[bcrypt]
Requires-Dist: python-jose[cryptography]
Requires-Dist: cachetools
Requires-Dist: fustor-registry-client
Provides-Extra: dev
Requires-Dist: pytest>=8.0.0; extra == "dev"
Requires-Dist: ruff>=0.1.0; extra == "dev"
Requires-Dist: mypy>=1.0.0; extra == "dev"
Requires-Dist: pytest-asyncio>=0.23.0; extra == "dev"
